{ "id": "purenumerals",
  "name": "Pure Numerals Clock",
  "shortName":"Pure Numerals",
  "icon": "app.png",
  "version":"0.04",
  "author":"OST Eastern Switzerland University of Applied Sciences",
  "description": "Pure Numerals is a minimalist digital watch face that displays easy-to-read time and date as two bold blocks of numbers in vivid colors on a deep black background. It also includes a step counter, heart rate measurement, a flashlight and a battery indicator.",
  "tags": "clock",
  "type": "clock",
  "supports": ["BANGLEJS2"],
  "allow_emulator": true,
  "readme":"README.md",
  "storage": [
    {"name":"purenumerals.app.js","url":"app.js"},
    {"name":"purenumerals.img","url":"app-icon.js","evaluate":true}
  ],
  "screenshots": [{"url":"screenshot.png"}]
}