{ "id": "analogquadclk",
  "name": "Analog Quad Clock",
  "shortName":"Quad Clock",
  "version":"0.02",
  "description": "An analog clock with clockinfos in each of the 4 corners, allowing 4 different data types to be rendered at once",
  "icon": "icon.png",
  "screenshots" : [ { "url":"screenshot.png" }, { "url":"screenshot2.png" } ],
  "type": "clock",
  "tags": "clock,clkinfo,analog",
  "supports" : ["BANGLEJS2"],
  "dependencies" : { "clock_info":"module", "clockbg":"module" },
  "storage": [
    {"name":"analogquadclk.app.js","url":"app.js"},
    {"name":"analogquadclk.img","url":"app-icon.js","evaluate":true}
  ]
}
