{ 
  "id": "ultrainfo",
  "name": "Ultra Info Clock",
  "shortName":"Ultra Info",
  "icon": "icon.png",
  "version":"0.01",
  "description": "The ultimate information clock with 10 clockinfos - for those who crave as much information as possible on their wrists.",
  "type":"clock",    
  "tags": "clock,clkinfo",
  "author":"RKBoss6",
  "supports": ["BANGLEJS2"],
  "dependencies" : { "clockbg":"module","clkinfoclk":"app", "clock_info":"module"},
  "allow_emulator":true,
  "readme":"README.md",
  "storage": [
    {"name":"ultrainfo.app.js","url":"app.js"},
    {"name":"ultrainfo.img","url":"app-icon.js","evaluate":true}
  ]
}
